./LICENSE
./PKG-INFO
./README.md
./__init__.py
./openapi.json
./pyproject.toml
./server.py
bach_find_any_ip_address_or_domain_location_world_wide-1.0.0.dist-info/METADATA
bach_find_any_ip_address_or_domain_location_world_wide-1.0.0.dist-info/WHEEL
bach_find_any_ip_address_or_domain_location_world_wide-1.0.0.dist-info/entry_points.txt
bach_find_any_ip_address_or_domain_location_world_wide-1.0.0.dist-info/licenses/LICENSE
bach_find_any_ip_address_or_domain_location_world_wide-1.0.0.dist-info/RECORD
